azure/mgmt/dataprotection/__init__.py
azure/mgmt/dataprotection/_client.py
azure/mgmt/dataprotection/_configuration.py
azure/mgmt/dataprotection/_patch.py
azure/mgmt/dataprotection/_version.py
azure/mgmt/dataprotection/py.typed
azure/mgmt/dataprotection/_utils/__init__.py
azure/mgmt/dataprotection/_utils/model_base.py
azure/mgmt/dataprotection/_utils/serialization.py
azure/mgmt/dataprotection/aio/__init__.py
azure/mgmt/dataprotection/aio/_client.py
azure/mgmt/dataprotection/aio/_configuration.py
azure/mgmt/dataprotection/aio/_patch.py
azure/mgmt/dataprotection/aio/operations/__init__.py
azure/mgmt/dataprotection/aio/operations/_operations.py
azure/mgmt/dataprotection/aio/operations/_patch.py
azure/mgmt/dataprotection/models/__init__.py
azure/mgmt/dataprotection/models/_enums.py
azure/mgmt/dataprotection/models/_models.py
azure/mgmt/dataprotection/models/_patch.py
azure/mgmt/dataprotection/operations/__init__.py
azure/mgmt/dataprotection/operations/_operations.py
azure/mgmt/dataprotection/operations/_patch.py
azure_mgmt_dataprotection-2.0.1.dist-info/licenses/LICENSE
azure_mgmt_dataprotection-2.0.1.dist-info/licenses/LICENSE.txt
azure_mgmt_dataprotection-2.0.1.dist-info/METADATA
azure_mgmt_dataprotection-2.0.1.dist-info/WHEEL
azure_mgmt_dataprotection-2.0.1.dist-info/top_level.txt
azure_mgmt_dataprotection-2.0.1.dist-info/RECORD
